{
  "name": "Lightning Dinosaurs",
  "show": "Dinosaur King",
  "trope_count": 33,
  "tropes": [
    "TrappedInAnotherWorld",
    "ColorCodedElements",
    "CrazyJealousGuy",
    "NonIndicativeName",
    "SummonMagic",
    "Determinator",
    "AlasPoorVillain",
    "MagicEnhancement",
    "FishOutOfTemporalWater",
    "SingleTear",
    "DeadlyDustStorm",
    "ReusedCharacterDesign",
    "WhatHappenedToTheMouse",
    "ArtisticLicensePaleontology",
    "BadassNormal",
    "Fartillery",
    "ShockAndAwe",
    "DualBoss",
    "SensoryOverload",
    "RecurringBoss",
    "RoaringRampageOfRevenge",
    "TemperCeratops",
    "StealthyColossus",
    "BodyPaint",
    "FightingYourFriend",
    "AdaptationalBadass",
    "WeHardlyKnewYe",
    "ManlyTears",
    "GuestStarPartyMember",
    "HeadButtingPachy",
    "CargoShip",
    "MonumentalDamage",
    "BrainwashedAndCrazy"
  ],
  "tropes_by_category": {}
}