{
  "name": "Gwizdo",
  "show": "Dragon Hunters",
  "trope_count": 81,
  "tropes": [
    "IdiotHair",
    "SuperDrowningSkills",
    "AntiHero",
    "EveryoneHasStandards",
    "LovableRogue",
    "HeroicBSOD",
    "RudeHeroNiceSidekick",
    "WeakButSkilled",
    "HiddenDepths",
    "UnsympatheticComedyProtagonist",
    "LovableCoward",
    "MasculineGirlFeminineBoy",
    "MotorMouth",
    "AdaptationDyeJob",
    "BigOlEyebrows",
    "StepfordSnarker",
    "TookALevelInKindness",
    "AdaptationalUgliness",
    "CowardlyLion",
    "NonActionGuy",
    "BigBrotherInstinct",
    "WhatTheHellHero",
    "HammyHerald",
    "BrooklynRage",
    "KickTheDog",
    "LeParkour",
    "DeathWorld",
    "WordOfGod",
    "BoisterousWeakling",
    "SmallNameBigEgo",
    "CommitmentIssues",
    "ChildhoodFriend",
    "DisguisedInDrag",
    "DirtyCoward",
    "NeverBareheaded",
    "BruiserWithASoftCenter",
    "HeroicWillpower",
    "HonestJohnsDealership",
    "ShorterMeansSmarter",
    "OlderThanTheyLook",
    "BadassBookworm",
    "Determinator",
    "TalkingInYourSleep",
    "FreudianExcuse",
    "AbledInTheAdaptation",
    "BoundAndGagged",
    "DeadpanSnarker",
    "NerdsAreNaive",
    "ProgressivelyPrettier",
    "CurtainsMatchTheWindow",
    "TheEmpath",
    "ConvenientlyAnOrphan",
    "NominalHero",
    "ZanyScheme",
    "TheNapoleon",
    "MilesGloriosus",
    "YoungerThanTheyLook",
    "BrainsAndBrawn",
    "RedOniBlueOni",
    "TooDumbToLive",
    "InSeriesNickname",
    "NotAMorningPerson",
    "MusclesAreMeaningless",
    "AcePilot",
    "MessyHair",
    "ButtMonkey",
    "JerkWithAHeartOfGold",
    "DistressedDude",
    "ManChild",
    "Joisey",
    "TheUnfavorite",
    "SandInMyEyes",
    "ImpossiblyCoolClothes",
    "GoMadFromTheRevelation",
    "MrViceGuy",
    "BigGuyLittleGuy",
    "Catchphrase",
    "AffectionHatingKid",
    "TookALevelInBadass",
    "ItsPersonal",
    "HeterosexualLifePartners"
  ],
  "tropes_by_category": {}
}