{
  "name": "The Brain",
  "show": "Pinky and the Brain",
  "trope_count": 108,
  "tropes": [
    "UtopiaJustifiesTheMeans",
    "AntiHero",
    "YouCantThwartStageOne",
    "HiddenHeartOfGold",
    "AffablyEvil",
    "IntellectualAnimal",
    "TechnicalPacifist",
    "VocalEvolution",
    "MultipleChoicePast",
    "TookALevelInJerkass",
    "DubNameChange",
    "AwesomenessByAnalysis",
    "TheDeterminator",
    "ThrowTheDogABone",
    "CityMouse",
    "MyBrainIsBig",
    "MyGodWhatHaveIDone",
    "TheComicallySerious",
    "AntiVillain",
    "EvenEvilHasStandards",
    "Antihero",
    "AmbiguouslyEvil",
    "BigBad",
    "CharacterDevelopment",
    "ChekhovsGun",
    "NoCelebritiesWereHarmed",
    "AdaptationalVillainy",
    "InsufferableGenius",
    "FatalFlaw",
    "ResearcherRodent",
    "VerySpecialEpisode",
    "OnlySaneByComparison",
    "UptightLovesWild",
    "KickTheDog",
    "VitriolicBestBuds",
    "WeAreAsMayflies",
    "NobleDemon",
    "MobileSuitHuman",
    "TropeNamer",
    "EvilGenius",
    "CartoonyTail",
    "VillainProtagonist",
    "HalloweenSpecial",
    "ArchEnemy",
    "ParentalAbandonment",
    "Workaholic",
    "TakeOverTheWorld",
    "ShorterMeansSmarter",
    "SpinOff",
    "DatedHistory",
    "WellIntentionedExtremist",
    "Determinator",
    "FreudianExcuse",
    "IronButtMonkey",
    "GuileHero",
    "DeadpanSnarker",
    "FailureIsTheOnlyOption",
    "DidntThinkThisThrough",
    "MyGreatestFailure",
    "TheNapoleon",
    "FutureMeScaresMe",
    "HisOwnWorstEnemy",
    "IndyPloy",
    "SophisticatedAsHell",
    "InsaneTrollLogic",
    "LargeHam",
    "KavorkaMan",
    "BigYes",
    "MeaningfulRename",
    "TheLoad",
    "SpellMyNameWithAThe",
    "LaughablyEvil",
    "ForeheadOfDoom",
    "IgnoredEpiphany",
    "PragmaticVillainy",
    "BerserkButton",
    "SpannerInTheWorks",
    "SesquipedalianLoquaciousness",
    "VillainsNeverLie",
    "HoistByHisOwnPetard",
    "BadBadActing",
    "MoodSwinger",
    "DitzyGenius",
    "MindControl",
    "JerkWithAHeartOfGold",
    "NeverMyFault",
    "AreYouPonderingWhatImPondering",
    "PaperThinDisguise",
    "HeWhoFightsMonsters",
    "AdaptationalJerkass",
    "UpliftedAnimal",
    "BornLucky",
    "MadScientist",
    "TakeThat",
    "FriendlyEnemy",
    "VocalDissonance",
    "Cloudcuckoolander",
    "TVGenius",
    "BreakTheHaughty",
    "SarcasticConfession",
    "FourLegsGoodTwoLegsBetter",
    "MoralityPet",
    "GadgeteerGenius",
    "EnragedByIdiocy",
    "DrBrainpart",
    "Catchphrase",
    "HeterosexualLifePartners",
    "CreativeSterility"
  ],
  "tropes_by_category": {}
}