{
  "name": "Princess Lotta Lamour",
  "show": "TaleSpin",
  "trope_count": 16,
  "tropes": [
    "AffectionateParody",
    "FoxyVixen",
    "Expy",
    "HorribleJudgeOfCharacter",
    "BrainyBrunette",
    "PrettyPrincessPowerhouse",
    "EvilChancellor",
    "PunnyName",
    "ReasonableAuthorityFigure",
    "Mooks",
    "BumblingDad",
    "ObviouslyEvil",
    "RoyalsWhoActuallyDoSomething",
    "NiceGirl",
    "CassandraTruth",
    "EverythingSoundsSexierInFrench"
  ],
  "tropes_by_category": {}
}