{
  "name": "The Ant Hill Mob (Drivers of the Bulletproof Bomb)",
  "show": "Wacky Races",
  "trope_count": 18,
  "tropes": [
    "BankRobbery",
    "TheFamilyForTheWholeFamily",
    "NoCelebritiesWereHarmed",
    "DivergentCharacterEvolution",
    "ThePiratesWhoDontDoAnything",
    "PaperThinDisguise",
    "TheRoaring20s",
    "BoringButPractical",
    "NoNameGiven",
    "RunningOnTheSpot",
    "VirtuousCharacterCopy",
    "PunchClockVillain",
    "DubNameChange",
    "EarlyInstallmentWeirdness",
    "SolidCartoonFacialStubble",
    "CharacterizationMarchesOn",
    "RecoilBoost",
    "ComicBookFantasyCasting"
  ],
  "tropes_by_category": {}
}