{
  "name": "Mel Karnofsky",
  "show": "Frasier",
  "trope_count": 24,
  "tropes": [
    "FemaleMisogynist",
    "OlderThanTheyLook",
    "EntitledBitch",
    "HowTheyTreatTheHelp",
    "EvilIsPetty",
    "WomanScorned",
    "JerkWithAHeartOfGold",
    "LadyMacbeth",
    "GenderBlenderName",
    "SpoiledBrat",
    "SuspiciouslySimilarSubstitute",
    "TookALevelInJerkass",
    "KickTheDog",
    "TheParanoiac",
    "JerkassHasAPoint",
    "OvercomplicatedMenuOrder",
    "ClingyJealousGirl",
    "BullyingADragon",
    "ICantDance",
    "AbortedArc",
    "ControlFreak",
    "YourLittleDismissiveDiminutive",
    "ManipulativeBitch",
    "RichBitch"
  ],
  "tropes_by_category": {}
}