{
  "name": "Delle Seyah Kendry",
  "show": "Killjoys",
  "trope_count": 29,
  "tropes": [
    "IWasJustJoking",
    "ScrewTheRulesIMakeThem",
    "EvenEvilHasLovedOnes",
    "LeftForDead",
    "ChronicBackstabbingDisorder",
    "KnownOnlyByTheirNickname",
    "MoralityChain",
    "BlueBlood",
    "AffablyEvil",
    "DeadpanSnarker",
    "ButchLesbian",
    "TheChessmaster",
    "GoodIsNotNice",
    "TheStraightAndArrowPath",
    "GodSaveUsFromTheQueen",
    "AmbiguouslyGay",
    "BreakTheHaughty",
    "AmbiguouslyHuman",
    "MamaBear",
    "BroughtDownToBadass",
    "CorruptCorporateExecutive",
    "Irony",
    "HeelFaceTurn",
    "FoeRomanceSubtext",
    "TookALevelInKindness",
    "StraightGay",
    "AwesomeByAnalysis",
    "LipstickLesbian",
    "RichBitch"
  ],
  "tropes_by_category": {}
}