{
  "name": "R.E.G.I.S. Mark  5",
  "show": "Megas XLR",
  "trope_count": 17,
  "tropes": [
    "AffablyEvil",
    "VoiceOfTheLegion",
    "FromASingleCell",
    "MonsterOfTheWeek",
    "Leitmotif",
    "NotSoHarmlessVillain",
    "PetTheDog",
    "WhatHappenedToTheMouse",
    "AchillesHeel",
    "BadassBoast",
    "KilledMidSentence",
    "IAmLegion",
    "NonStandardCharacterDesign",
    "TheComicallySerious",
    "AsteroidsMonster",
    "MakeMyMonsterGrow",
    "FunWithAcronyms"
  ],
  "tropes_by_category": {}
}