{
  "name": "The Riceballs",
  "show": "Osomatsu-san",
  "trope_count": 23,
  "tropes": [
    "IdenticalTwinIDTag",
    "BerserkButton",
    "GrewBeyondTheirProgramming",
    "CatGirl",
    "CatchPhrase",
    "DivergentCharacterEvolution",
    "BrutalHonesty",
    "TagalongKid",
    "TookALevelInJerkass",
    "HiddenDepths",
    "BokeAndTsukkomiRoutine",
    "CuteMachines",
    "SecondEpisodeIntroduction",
    "EdibleThemeNaming",
    "TheDividual",
    "AnnoyingYoungerSibling",
    "SensitiveGuyAndManlyMan",
    "AllOfTheOtherReindeer",
    "OnlySaneMan",
    "InnocentlyInsensitive",
    "WithFriendsLikeThese",
    "ControlFreak",
    "AIs"
  ],
  "tropes_by_category": {}
}