{
  "name": "Ronald \"Ron\"MacDougall",
  "show": "Outlaw Star",
  "trope_count": 26,
  "tropes": [
    "Cyborg",
    "TrueCompanions",
    "BigBrotherMentor",
    "RevengeMyopia",
    "BadassLongcoat",
    "ParentalSubstitute",
    "AffablyEvil",
    "BeamOWar",
    "BigBrotherInstinct",
    "KilledMidSentence",
    "BadassNormal",
    "HeroKiller",
    "SmugSnake",
    "WickedCultured",
    "ButForMeItWasTuesday",
    "DangerousForbiddenTechnique",
    "VillainousBreakdown",
    "VillainHasAPoint",
    "OhCrap",
    "Archenemy",
    "OldFlame",
    "RedOniBlueOni",
    "TemptingFate",
    "ProfessionalKiller",
    "EvilCounterpart",
    "GoodScarsEvilScars"
  ],
  "tropes_by_category": {}
}